setup.py
HTML/Auto.py
HTML/__init__.py
Spreadsheet/HTML.py
Spreadsheet/__init__.py
Spreadsheet_HTML.egg-info/PKG-INFO
Spreadsheet_HTML.egg-info/SOURCES.txt
Spreadsheet_HTML.egg-info/dependency_links.txt
Spreadsheet_HTML.egg-info/requires.txt
Spreadsheet_HTML.egg-info/top_level.txt