Metadata-Version: 2.1
Name: Spreadsheet-HTML
Version: 0.0.4
Summary: Just another HTML table generator (for Python)
Home-page: https://github.com/jeffa/Spreadsheet-HTML-python
Author: Jeff Anderson
Author-email: jeffa@cpan.org
License: Artistic
Platform: UNKNOWN
Classifier: Topic :: Text Processing :: Markup :: HTML
Classifier: Development Status :: 1 - Planning
Classifier: Intended Audience :: Developers
Classifier: Programming Language :: Python
Classifier: Programming Language :: Python :: 3
Classifier: Operating System :: OS Independent
Classifier: License :: OSI Approved :: Artistic License
